xero/__init__.py
xero/api_helper.py
xero/configuration.py
xero/xero_client.py
xero/controllers/__init__.py
xero/controllers/account_id_controller.py
xero/controllers/accounts_controller.py
xero/controllers/attachments_controller.py
xero/controllers/bank_transaction_id_controller.py
xero/controllers/bank_transactions_controller.py
xero/controllers/bank_transfer_id_controller.py
xero/controllers/bank_transfers_controller.py
xero/controllers/base_controller.py
xero/controllers/batch_payment_id_history_controller.py
xero/controllers/batch_payments_controller.py
xero/controllers/branding_theme_id_controller.py
xero/controllers/branding_themes_controller.py
xero/controllers/contact_group_id_controller.py
xero/controllers/contact_groups_controller.py
xero/controllers/contact_id_controller.py
xero/controllers/contacts_controller.py
xero/controllers/credit_note_id_controller.py
xero/controllers/credit_notes_controller.py
xero/controllers/currencies_controller.py
xero/controllers/employees_controller.py
xero/controllers/expense_claim_id_controller.py
xero/controllers/expense_claims_controller.py
xero/controllers/file_name_controller.py
xero/controllers/history_controller.py
xero/controllers/invoice_id_controller.py
xero/controllers/invoices_controller.py
xero/controllers/item_id_controller.py
xero/controllers/items_controller.py
xero/controllers/journals_controller.py
xero/controllers/linked_transaction_id_controller.py
xero/controllers/linked_transactions_controller.py
xero/controllers/manual_journal_id_controller.py
xero/controllers/manual_journals_controller.py
xero/controllers/misc_controller.py
xero/controllers/options_controller.py
xero/controllers/organisation_controller.py
xero/controllers/overpayment_id_controller.py
xero/controllers/overpayments_controller.py
xero/controllers/payment_id_controller.py
xero/controllers/payment_services_controller.py
xero/controllers/payments_controller.py
xero/controllers/prepayment_id_controller.py
xero_accounting_sdk-1.0.0.dist-info/licenses/LICENSE
xero_accounting_sdk-1.0.0.dist-info/METADATA
xero_accounting_sdk-1.0.0.dist-info/WHEEL
xero_accounting_sdk-1.0.0.dist-info/top_level.txt
xero_accounting_sdk-1.0.0.dist-info/RECORD
