Metadata-Version: 2.4
Name: xero-accounting-sdk
Version: 1.0.0
Summary: Xero's Accounting API that contains all the endpoints for managing accounting operations including accounts, attachments, batch payments, bank transactions, and other financial data.
Author-email: Muhammad Hamza Shahzad <muhammad.hamza@apimatic.io>
Project-URL: Documentation, https://docs.apimatic.io/
Requires-Python: >=3.7
License-File: LICENSE
Requires-Dist: apimatic-core>=0.2.20,~=0.2.0
Requires-Dist: apimatic-core-interfaces>=0.1.5,~=0.1.0
Requires-Dist: apimatic-requests-client-adapter>=0.1.6,~=0.1.0
Provides-Extra: testutils
Requires-Dist: pytest>=7.2.2; extra == "testutils"
Dynamic: license-file
